collective.solr-10.1.0-py3.12-nspkg.pth
collective/solr/__init__.py
collective/solr/attributes.py
collective/solr/behaviors.py
collective/solr/commands.py
collective/solr/configure.zcml
collective/solr/contentlisting.py
collective/solr/dispatcher.py
collective/solr/events.py
collective/solr/exceptions.py
collective/solr/extender.py
collective/solr/extender.zcml
collective/solr/flare.py
collective/solr/indexer.py
collective/solr/interfaces.py
collective/solr/lingua.py
collective/solr/local.py
collective/solr/manager.py
collective/solr/mangler.py
collective/solr/meta.zcml
collective/solr/monkey.py
collective/solr/parser.py
collective/solr/profiles.zcml
collective/solr/queryparser.py
collective/solr/search.py
collective/solr/serializer.py
collective/solr/setuphandlers.py
collective/solr/solr.py
collective/solr/stopword.py
collective/solr/testing.py
collective/solr/upgrades.zcml
collective/solr/utils.py
collective/solr/vocabularies.py
collective/solr/zcml.py
collective/solr/browser/__init__.py
collective/solr/browser/configure.zcml
collective/solr/browser/controlpanel.py
collective/solr/browser/errors.py
collective/solr/browser/facets.py
collective/solr/browser/interfaces.py
collective/solr/browser/maintenance.py
collective/solr/browser/suggest.py
collective/solr/browser/images/icon.png
collective/solr/browser/resources/style.css
collective/solr/browser/templates/controlpanel.pt
collective/solr/browser/templates/errors.pt
collective/solr/browser/templates/facets.pt
collective/solr/browser/templates/hiddenfields.pt
collective/solr/browser/templates/search.pt
collective/solr/browser/templates/searchbox.pt
collective/solr/locales/rebuildPo.sh
collective/solr/locales/solr.pot
collective/solr/locales/de/LC_MESSAGES/solr.mo
collective/solr/locales/de/LC_MESSAGES/solr.po
collective/solr/locales/en/LC_MESSAGES/solr.mo
collective/solr/locales/en/LC_MESSAGES/solr.po
collective/solr/locales/fr/LC_MESSAGES/solr.mo
collective/solr/locales/fr/LC_MESSAGES/solr.po
collective_solr-10.1.0.dist-info/METADATA
collective_solr-10.1.0.dist-info/WHEEL
collective_solr-10.1.0.dist-info/entry_points.txt
collective_solr-10.1.0.dist-info/namespace_packages.txt
collective_solr-10.1.0.dist-info/top_level.txt
collective_solr-10.1.0.dist-info/RECORD
