Metadata-Version: 2.4
Name: collective.solr
Version: 10.1.0
Summary: Solr integration for external indexing and searching.
Home-page: https://github.com/collective/collective.solr
Author: Plone Community
Author-email: plone-developers@lists.sourceforge.net
Maintainer: Timo Stollenwerk
Maintainer-email: tisto@plone.org
License: GPL version 2
Keywords: plone cmf zope indexing searching solr lucene
Platform: Any
Classifier: Development Status :: 5 - Production/Stable
Classifier: Environment :: Web Environment
Classifier: Framework :: Plone
Classifier: Framework :: Plone :: 6.0
Classifier: Framework :: Plone :: 6.1
Classifier: Framework :: Plone :: Addon
Classifier: Intended Audience :: Developers
Classifier: Intended Audience :: System Administrators
Classifier: Intended Audience :: Other Audience
Classifier: License :: OSI Approved :: GNU General Public License (GPL)
Classifier: Operating System :: OS Independent
Classifier: Programming Language :: Python
Classifier: Programming Language :: Python :: 3 :: Only
Classifier: Programming Language :: Python :: 3.10
Classifier: Programming Language :: Python :: 3.11
Classifier: Programming Language :: Python :: 3.12
Classifier: Programming Language :: Python :: 3.13
Requires-Dist: Acquisition
Requires-Dist: DateTime
Requires-Dist: Products.CMFCore
Requires-Dist: Products.CMFPlone>=6.0.0
Requires-Dist: Products.GenericSetup
Requires-Dist: Products.ZCatalog
Requires-Dist: lxml
Requires-Dist: plone.app.content
Requires-Dist: plone.app.layout
Requires-Dist: plone.app.registry
Requires-Dist: plone.app.vocabularies
Requires-Dist: plone.api
Requires-Dist: plone.browserlayer
Requires-Dist: plone.indexer
Requires-Dist: plone.restapi
Requires-Dist: requests-toolbelt
Requires-Dist: setuptools
Requires-Dist: transaction
Requires-Dist: zope.component
Requires-Dist: zope.i18nmessageid
Requires-Dist: zope.interface
Requires-Dist: zope.publisher
Requires-Dist: zope.schema
Provides-Extra: test
Requires-Dist: plone.app.testing[robot]; extra == "test"
Requires-Dist: plone.app.robotframework[debug]; extra == "test"
Dynamic: author
Dynamic: author-email
Dynamic: classifier
Dynamic: description
Dynamic: home-page
Dynamic: keywords
Dynamic: license
Dynamic: maintainer
Dynamic: maintainer-email
Dynamic: platform
Dynamic: provides-extra
Dynamic: requires-dist
Dynamic: summary
